copier_pydantic/__init__.py
copier_pydantic/multiline_validation.py
copier_pydantic/py.typed
copier_pydantic/validators.py
copier_pydantic-0.1.3.dist-info/licenses/LICENSE
copier_pydantic-0.1.3.dist-info/WHEEL
copier_pydantic-0.1.3.dist-info/METADATA
copier_pydantic-0.1.3.dist-info/RECORD
