Metadata-Version: 2.4
Name: copier-pydantic
Version: 0.1.3
Summary: Adds support for Pydantic Models in Copier templates
Author: Chris Brown
Author-email: Chris Brown <cbrown1234@hotmail.co.uk>
License-Expression: MIT
License-File: LICENSE
Requires-Dist: copier>=3.6
Requires-Python: >=3.13
